{"cameraMode":{"drawMode":0,"name":"Shaded","section":"Shading Mode"},"sceneLighting":true,"audioPlay":false,"sceneViewState":{"m_AlwaysRefresh":false,"showFog":true,"showSkybox":true,"showFlares":true,"showImageEffects":true,"showParticleSystems":true,"showVisualEffectGraphs":true,"m_FxEnabled":true},"in2DMode":false,"pivot":{"x":-122.41837310791016,"y":-131.2679443359375,"z":46.692203521728519},"rotation":{"x":-0.5522245764732361,"y":-0.0126954922452569,"z":0.008604615926742554,"w":-0.8337575197219849},"size":119.82356262207031,"orthographic":false}